<?xml version="1.0" encoding="UTF-8" ?>
<xmldoc>
  <copyright>SAME AS NELSON SOFTWARE</copyright>
  <language>fr_FR</language>
  <keyword>diary</keyword>
  <short_description>Journal d&apos;une session.</short_description>
  <syntax>
    <syntax_item>diary()</syntax_item>
    <syntax_item>diary(filename)</syntax_item>
    <syntax_item>diary(&apos;off&apos;)</syntax_item>
    <syntax_item>diary(&apos;on&apos;)</syntax_item>
    <syntax_item>onoff = diary(&apos;get&apos;, &apos;Diary&apos;)</syntax_item>
    <syntax_item>filename = diary(&apos;get&apos;, &apos;DiaryFile&apos;)</syntax_item>
    <syntax_item>diary(&apos;set&apos;, &apos;DiaryFile&apos;, filename)</syntax_item>
    <syntax_item>diary(&apos;set&apos;, &apos;Diary&apos;, onoff)</syntax_item>
  </syntax>
  <param_input>
    <param_input_item>
      <param_name>onoff</param_name>
      <param_description>une chaîne : &apos;on&apos; ou &apos;off&apos;.</param_description>
    </param_input_item>
    <param_input_item>
      <param_name>filename</param_name>
      <param_description
      >une chaîne : nom de fichier du journal courant.</param_description>
    </param_input_item>
  </param_input>
  <param_output>
    <param_output_item>
      <param_name>onoff</param_name>
      <param_description>une chaîne : &apos;on&apos; ou &apos;off&apos;.</param_description>
    </param_output_item>
    <param_output_item>
      <param_name>filename</param_name>
      <param_description
      >une chaîne : nom de fichier à utiliser pour le journal.</param_description>
    </param_output_item>
  </param_output>
  <description>
    <p>
      <b
      >diary</b> crée un journal des entrées clavier et du texte de sortie résultant.</p>
    <p>
      <b>diary</b> active ou désactive le mode journal.</p>
    <p>
      <b
      >diary(&apos;off&apos;)</b> arrête l&apos;enregistrement de la session dans le fichier journal.</p>
    <p>
      <b
      >diary(&apos;on&apos;)</b> commence l&apos;enregistrement d&apos;une session dans un fichier nommé &apos;diary&apos; dans le répertoire de travail courant.</p>
    <p>
      <b
      >diary(&apos;set&apos;, &apos;Diary&apos;, onoff)</b> permet de démarrer ou d&apos;arrêter le journal.</p>
    <p>
      <b
      >onoff = diary(&apos;get&apos;, &apos;Diary&apos;)</b> renvoie l&apos;état &apos;on&apos; ou &apos;off&apos; du journal.</p>
    <p>
      <b
      >diary(filename)</b> enregistre la session dans le fichier nommé filename.</p>
    <p>
      <b
      >filename = diary(&apos;get&apos;, &apos;DiaryFile&apos;)</b> renvoie le nom de fichier utilisé pour le journal.</p>
    <p>
      <b
      >diary(&apos;set&apos;, &apos;DiaryFile&apos;, filename))</b> définit le nom de fichier pour le journal.</p>
  </description>
  <used_function />
  <bibliography />
  <examples>
    <example_item>
      <example_item_type>nelson</example_item_type>
      <example_item_description />
      <example_item_data
        runnable="cli"
      ><![CDATA[filename = diary('get', 'DiaryFile')
onoff = diary('get', 'Diary')]]></example_item_data>
    </example_item>
  </examples>
  <see_also>
    <see_also_item>
      <link linkend="${history_manager}history">history</link>
    </see_also_item>
  </see_also>
  <history>
    <history_item>
      <history_version>1.0.0</history_version>
      <history_description>version initiale</history_description>
    </history_item>
  </history>
  <authors>
    <author_item>Allan CORNET</author_item>
  </authors>
</xmldoc>
