<?xml version="1.0" encoding="UTF-8" ?>
<xmldoc>
  <copyright>SAME AS NELSON SOFTWARE</copyright>
  <language>fr_FR</language>
  <keyword>audioplayer</keyword>
  <short_description>Objet audioplayer.</short_description>
  <syntax>
    <syntax_item>playerObj = audioplayer(y, fs)</syntax_item>
    <syntax_item>playerObj = audioplayer(y, fs, nbits)</syntax_item>
    <syntax_item>playerObj = audioplayer(y, fs, nbits, id)</syntax_item>
  </syntax>
  <param_input>
    <param_input_item>
      <param_name>y</param_name>
      <param_description
      >un vecteur ou une matrice : int8,uint8, int16, single ou double.</param_description>
    </param_input_item>
    <param_input_item>
      <param_name>fs</param_name>
      <param_description
      >une valeur double : fréquence d'échantillonnage en Hz.</param_description>
    </param_input_item>
    <param_input_item>
      <param_name>nbits</param_name>
      <param_description
      >une valeur double : nombre de bits par échantillon (16 par défaut).</param_description>
    </param_input_item>
    <param_input_item>
      <param_name>id</param_name>
      <param_description
      >une valeur double : identifiant du périphérique (-1 par défaut).</param_description>
    </param_input_item>
  </param_input>
  <param_output>
    <param_output_item>
      <param_name>playerObj</param_name>
      <param_description>audioplayer objet</param_description>
    </param_output_item>
  </param_output>
  <description>
    <p><b
      >audioplayer</b> renvoie un objet audioplayer pour lire des données sur un périphérique de sortie.</p>
    <p
    >L'objet audioplayer utilise une portée globale et doit être supprimé par l'utilisateur.</p>
    <p><b
      >audioplayer</b> peut lire des données multicanaux si votre carte son le supporte.</p>
    <p><b>Propriétés de audioplayer</b> :</p>
    <table>
      <tr>
        <th>Propriété</th>
        <th>Type / Valeurs</th>
        <th>Description</th>
      </tr>
      <tr>
        <td>SampleRate</td>
        <td> scalaire positif</td>
        <td
        >Taux d'échantillonnage en Hz. Défini via Fs lors de la création de l'objet ; ajustable par la suite.</td>
      </tr>
      <tr>
        <td>BitsPerSample</td>
        <td>Lecture seule : 8, 16, 24</td>
        <td>Bits par échantillon, déterminés par l'argument nBits.</td>
      </tr>
      <tr>
        <td>NumChannels</td>
        <td>Lecture seule : 1, 2</td>
        <td
        >Nombre de canaux mono (1) ou stéréo (2) rapporté par le lecteur.</td>
      </tr>
      <tr>
        <td>DeviceID</td>
        <td>Lecture seule : entier</td>
        <td>Identifiant du périphérique audio fourni via l'argument ID.</td>
      </tr>
      <tr>
        <td>CurrentSample</td>
        <td>Lecture seule : entier positif</td>
        <td
        >Échantillon actuellement en lecture ; lorsqu'il est inactif, le prochain échantillon que play/reprise utilisera.</td>
      </tr>
      <tr>
        <td>TotalSamples</td>
        <td>Lecture seule : entier non négatif</td>
        <td>Nombre total d'échantillons dans les données audio.</td>
      </tr>
      <tr>
        <td>Running</td>
        <td>Lecture seule : 'off' ou 'on'</td>
        <td>État du lecteur audio.</td>
      </tr>
      <tr>
        <td>StartFcn</td>
        <td>vecteur de caractères ou handle de fonction</td>
        <td
        >Callback exécuté au début de la lecture ; les premiers arguments sont l'audioplayer et une structure d'événement.</td>
      </tr>
      <tr>
        <td>StopFcn</td>
        <td>vecteur de caractères ou handle de fonction</td>
        <td
        >Callback exécuté à la fin de la lecture ; les premiers arguments sont l'audioplayer et une structure d'événement.</td>
      </tr>
      <tr>
        <td>TimerFcn</td>
        <td>vecteur de caractères ou handle de fonction</td>
        <td
        >Callback exécuté périodiquement pendant la lecture ; l'intervalle est contrôlé par TimerPeriod.</td>
      </tr>
      <tr>
        <td>TimerPeriod</td>
        <td>0.05 (par défaut) ou scalaire positif</td>
        <td>Secondes entre les callbacks TimerFcn.</td>
      </tr>
      <tr>
        <td>Tag</td>
        <td>scalaire de chaîne ou vecteur de caractères</td>
        <td>Étiquette pour l'objet audioplayer.</td>
      </tr>
      <tr>
        <td>UserData</td>
        <td>[] (par défaut) ou tout type de données</td>
        <td
        >Données arbitraires définies par l'utilisateur stockées avec l'objet.</td>
      </tr>
      <tr>
        <td>Type</td>
        <td>Lecture seule : 'audioplayer'</td>
        <td>Identifiant du nom de la classe pour l'objet.</td>
      </tr>
    </table>

  </description>
  <used_function />
  <bibliography />
  <examples>
    <example_item>
      <example_item_type>nelson</example_item_type>
      <example_item_description />
      <example_item_data
        runnable="cli"
      ><![CDATA[signal = rand(2, 44100) - 0.5;
playObj = audioplayer(signal, 44100, 16)
play(playObj)
sleep(2)
delete(playObj)
playObj]]></example_item_data>
    </example_item>

    <example_item>
      <example_item_type>nelson</example_item_type>
      <example_item_description>Exemple de callback</example_item_description>
      <example_item_data
        runnable="adv-cli"
      ><![CDATA[signal = rand(2, 44100) - 0.5;
playObj = audioplayer(signal, 44100, 16);
playObj.StartFcn = @(src, event) disp('Playback started');
playObj.StopFcn = @(src, event) disp('Playback stopped');
playObj
play(playObj)
]]></example_item_data>
    </example_item>

  </examples>
  <see_also>
    <see_also_item>
      <link linkend="${handle}delete">delete</link>
    </see_also_item>
    <see_also_item>
      <link linkend="${audio}play">play</link>
    </see_also_item>
    <see_also_item>
      <link linkend="${audio}stop">stop</link>
    </see_also_item>
    <see_also_item>
      <link linkend="${audio}resume">resume</link>
    </see_also_item>
    <see_also_item>
      <link linkend="${audio}pause">pause</link>
    </see_also_item>
  </see_also>
  <history>
    <history_item>
      <history_version>1.0.0</history_version>
      <history_description>version initiale</history_description>
    </history_item>
    <history_item>
      <history_version>1.16.0</history_version>
      <history_description
      >Callback StartFcn, StopFcn, TimerFcn ajoutés</history_description>
    </history_item>
  </history>
  <authors>
    <author_item>Allan CORNET</author_item>
  </authors>
</xmldoc>
