<?xml version="1.0" encoding="UTF-8" ?>
<xmldoc>
  <copyright>SAME AS NELSON SOFTWARE</copyright>
  <language>en_US</language>
  <keyword>enumeration</keyword>
  <short_description>Returns enumeration member names for a classdef enumeration class.</short_description>
  <syntax>
    <syntax_item>c = enumeration(obj)</syntax_item>
    <syntax_item>c = enumeration(className)</syntax_item>
  </syntax>
  <param_input>
    <param_input_item>
      <param_name>obj</param_name>
      <param_description>a classdef enumeration object</param_description>
    </param_input_item>
    <param_input_item>
      <param_name>className</param_name>
      <param_description>an enumeration class name as a string</param_description>
    </param_input_item>
  </param_input>
  <param_output>
    <param_output_item>
      <param_name>c</param_name>
      <param_description>a cell of strings</param_description>
    </param_output_item>
  </param_output>
  <description>
    <p>
      <b>enumeration</b> returns the public enumeration members declared by a classdef class.</p>
    <p>Enumeration members can be accessed as <b>ClassName.MemberName</b>.</p>
    <p>Enumeration members can pass constructor arguments; stored properties initialized by the constructor are copied to the member value.</p>
  </description>
  <used_function />
  <bibliography />
  <examples>
    <example_item>
      <example_item_type>nelson</example_item_type>
      <example_item_description>List enumeration members.</example_item_description>
      <example_item_data runnable="false"><![CDATA[d = [tempdir(), 'nelson_help_enumeration/'];
mkdir(d);
filewrite([d, '/NelsonHelpColor.m'], ["classdef NelsonHelpColor"; "  enumeration"; "    Red"; "    Blue"; "  end"; "end"]);
addpath(d);
members = enumeration('NelsonHelpColor')]]></example_item_data>
    </example_item>
    <example_item>
      <example_item_type>nelson</example_item_type>
      <example_item_description>Use constructor arguments in enumeration members.</example_item_description>
      <example_item_data runnable="false"><![CDATA[d = [tempdir(), 'nelson_help_enumeration_ctor/'];
if ~isdir(d)
  mkdir(d);
end
filewrite([d, '/NelsonHelpLevel.m'], ["classdef NelsonHelpLevel"; "  properties"; "    Code = 0"; "  end"; "  methods"; "    function obj = NelsonHelpLevel(code)"; "      if nargin > 0"; "        obj.Code = code;"; "      end"; "    end"; "  end"; "  enumeration"; "    Low(1)"; "    High(2)"; "  end"; "end"]);
addpath(d);
high = eval('NelsonHelpLevel.High');
high.Code]]></example_item_data>
    </example_item>
  </examples>
  <see_also>
    <see_also_item>
      <link linkend="${handle}metaclass">metaclass</link>
    </see_also_item>
    <see_also_item>
      <link linkend="${interpreter}classdef">classdef</link>
    </see_also_item>
  </see_also>
  <history>
    <history_item>
      <history_version>2.0.0</history_version>
      <history_description>classdef enumeration support added</history_description>
    </history_item>
  </history>
  <authors>
    <author_item>Allan CORNET</author_item>
  </authors>
</xmldoc>
