<?xml version="1.0" encoding="UTF-8" ?>
<xmldoc>
  <copyright>SAME AS NELSON SOFTWARE</copyright>
  <language>en_US</language>
  <keyword>notify</keyword>
  <short_description>Notifies listeners of a classdef event.</short_description>
  <syntax>
    <syntax_item>notify(obj, eventName)</syntax_item>
    <syntax_item>notify(obj, eventName, eventData)</syntax_item>
  </syntax>
  <param_input>
    <param_input_item>
      <param_name>obj</param_name>
      <param_description>a classdef handle object</param_description>
    </param_input_item>
    <param_input_item>
      <param_name>eventName</param_name>
      <param_description>an event name as a string</param_description>
    </param_input_item>
    <param_input_item>
      <param_name>eventData</param_name>
      <param_description>optional event data passed to listener callbacks</param_description>
    </param_input_item>
  </param_input>
  <description>
    <p>
      <b>notify</b> runs listener callbacks registered for a classdef handle object event.</p>
    <p>Callbacks receive the source object and the supplied event data.</p>
  </description>
  <used_function />
  <bibliography />
  <examples>
    <example_item>
      <example_item_type>nelson</example_item_type>
      <example_item_description>Notify listeners of an event.</example_item_description>
      <example_item_data runnable="false"><![CDATA[d = [tempdir(), 'nelson_help_notify/'];
mkdir(d);
filewrite([d, '/NelsonHelpNotifyCounter.m'], ["classdef NelsonHelpNotifyCounter < handle"; "  events"; "    CountChanged"; "  end"; "end"]);
addpath(d);
counter = NelsonHelpNotifyCounter();
lh = addlistener(counter, 'CountChanged', @(src, eventData) disp('changed'));
notify(counter, 'CountChanged');
delete(lh);
delete(counter)]]></example_item_data>
    </example_item>
  </examples>
  <see_also>
    <see_also_item>
      <link linkend="${handle}addlistener">addlistener</link>
    </see_also_item>
    <see_also_item>
      <link linkend="${handle}events">events</link>
    </see_also_item>
    <see_also_item>
      <link linkend="${interpreter}classdef">classdef</link>
    </see_also_item>
  </see_also>
  <history>
    <history_item>
      <history_version>2.0.0</history_version>
      <history_description>classdef event notification support added</history_description>
    </history_item>
  </history>
  <authors>
    <author_item>Allan CORNET</author_item>
  </authors>
</xmldoc>
